Metadata-Version: 2.1
Name: CypherIt
Version: 0.0.7
Summary: Renames all files and writes it with what ever you want. For more information check out my website:https://pypi.org/project/CypherIt/
Home-page: UNKNOWN
Author: Fawaz Bashiru
Author-email: fawazbashiru@gmail.com
License: MIT
Keywords: CypherIT
Platform: UNKNOWN
Classifier: Development Status :: 6 - Mature
Classifier: Intended Audience :: Education
Classifier: Operating System :: Microsoft :: Windows :: Windows 10
Classifier: License :: OSI Approved :: MIT License
Classifier: Programming Language :: Python :: 3
